tnseeker/Essential_Finder.py
tnseeker/__init__.py
tnseeker/__main__.py
tnseeker/insertions2plots.py
tnseeker/reads_trimmer.py
tnseeker/sam2insertions.py
tnseeker/data/true_negatives.fasta
tnseeker/data/true_positives.fasta
tnseeker/data/test/test.fasta
tnseeker/data/test/test.fastq.gz
tnseeker/data/test/test.gb
tnseeker/extras/__init__.py
tnseeker/extras/helper_functions.py
tnseeker/extras/possion_binom.py
tnseeker-1.2.dist-info/licenses/LICENSE
tnseeker-1.2.dist-info/METADATA
tnseeker-1.2.dist-info/WHEEL
tnseeker-1.2.dist-info/entry_points.txt
tnseeker-1.2.dist-info/top_level.txt
tnseeker-1.2.dist-info/RECORD
