Metadata-Version: 2.4
Name: tnseeker
Version: 1.2
Summary: TnSeeker
Home-page: https://github.com/afombravo/tnseeker
Author: Afonso M Bravo
Author-email: <afonsombravo@hotmail.com>
Keywords: tn-seq,essentiality,rb-seq
Classifier: Development Status :: 4 - Beta
Classifier: Intended Audience :: Science/Research
Classifier: Programming Language :: Python :: 3
Classifier: Operating System :: OS Independent
License-File: LICENSE
Requires-Dist: numpy
Requires-Dist: matplotlib>=3.8
Requires-Dist: pandas>=2.2.0
Requires-Dist: numba
Requires-Dist: biopython>=1.83
Requires-Dist: datetime>=5.4
Requires-Dist: argparse>=1.4.0
Requires-Dist: regex>=2023.12.25
Requires-Dist: multiprocess>=0.70.16
Requires-Dist: pathlib>=1.0.1
Requires-Dist: scipy>=1.12.0
Requires-Dist: seaborn>=0.13.2
Requires-Dist: statsmodels>=0.14.1
Requires-Dist: colorama
Requires-Dist: fast2q>=2.7.6
Requires-Dist: dataclasses
Requires-Dist: typing
Dynamic: author
Dynamic: author-email
Dynamic: classifier
Dynamic: description
Dynamic: description-content-type
Dynamic: home-page
Dynamic: keywords
Dynamic: license-file
Dynamic: requires-dist
Dynamic: summary
